<?xml version='1.0' encoding='UTF-8'?>
<smallbismark>
 <motif name='EVI1_HUMAN' id='EVI1_do' sample-size='153' sequence-count='117' coverage='0.7647058823529411' length='19'>
  <comment>HOCOMOCO v9; MAR2012; ChIPMunk v3.1</comment>
  <background>
   <a>0.25</a>
   <c>0.25</c>
   <g>0.25</g>
   <t>0.25</t>
  </background>
  <consensus>dvhdAGAYAAGATARnMdd</consensus>
  <WPCM words-count='118.923780874097' length='19' dic='-13.341353077094775' kdic='12.998239784183168'>
   <pm-column position='1' dic='-1.2624903080943155' kdic='0.1238040530255748'>
    <a>30.445547500762554</a>
    <c>18.119694887114985</c>
    <g>47.067796129741375</g>
    <t>23.29074235647809</t>
   </pm-column>
   <pm-column position='2' dic='-1.0729921409937586' kdic='0.31330222012613185'>
    <a>69.07218172344763</a>
    <c>21.964746012534405</c>
    <g>15.247266595265936</g>
    <t>12.639586542849027</t>
   </pm-column>
   <pm-column position='3' dic='-1.2179349576415375' kdic='0.1683594034783531'>
    <a>44.41113038755527</a>
    <c>30.936531971846353</c>
    <g>9.28084683421478</g>
    <t>34.29527168048059</t>
   </pm-column>
   <pm-column position='4' dic='-1.1530617573373023' kdic='0.2332326037825874'>
    <a>57.979027128503965</a>
    <c>10.209157032314511</c>
    <g>19.887690012373273</g>
    <t>30.84790670090518</t>
   </pm-column>
   <pm-column position='5' dic='-0.643981408425648' kdic='0.7423129526942439'>
    <a>93.64928084269768</a>
    <c>0.8396849271585636</c>
    <g>10.164844396843925</g>
    <t>14.26997070739695</t>
   </pm-column>
   <pm-column position='6' dic='-0.25170837676398783' kdic='1.1345859843559045'>
    <a>1.6793698543171296</a>
    <c>3.8007384899488255</c>
    <g>111.85760100075395</g>
    <t>1.5860715290772898</t>
   </pm-column>
   <pm-column position='7' dic='-0.03374418851274059' kdic='1.3525501726071538'>
    <a>118.08409594693875</a>
    <c>0.0</c>
    <g>0.0</g>
    <t>0.8396849271585636</t>
   </pm-column>
   <pm-column position='8' dic='-0.7806503526954008' kdic='0.6056440084244911'>
    <a>4.640423417107397</a>
    <c>39.77070697044793</c>
    <g>0.8396849271585636</g>
    <t>73.67296555938324</t>
   </pm-column>
   <pm-column position='9' dic='-0.23692336041937645' kdic='1.1493710007005173'>
    <a>112.1619888213582</a>
    <c>4.242737271263404</c>
    <g>1.6793698543171296</g>
    <t>0.8396849271585636</t>
   </pm-column>
   <pm-column position='10' dic='-0.23848741451342356' kdic='1.1478069466064698'>
    <a>111.76430267551416</a>
    <c>0.0</c>
    <g>2.121368635631696</g>
    <t>5.038109562951377</t>
   </pm-column>
   <pm-column position='11' dic='-0.16690464072168137' kdic='1.2193897203982127'>
    <a>0.0</a>
    <c>3.403052344104833</c>
    <g>114.23904482151933</g>
    <t>1.2816837084731372</t>
   </pm-column>
   <pm-column position='12' dic='-0.15180888596986264' kdic='1.2344854751500314'>
    <a>114.23904482151933</a>
    <c>0.0</c>
    <g>0.0</g>
    <t>4.6847360525779695</t>
   </pm-column>
   <pm-column position='13' dic='-0.26170503542809265' kdic='1.1245893256918'>
    <a>0.0</a>
    <c>8.087788396682802</c>
    <g>0.7463866019187237</g>
    <t>110.08960587549566</t>
   </pm-column>
   <pm-column position='14' dic='-0.38997394054155615' kdic='0.9963204205783363'>
    <a>105.31157149767783</a>
    <c>0.0</c>
    <g>3.403052344104833</g>
    <t>10.209157032314511</t>
   </pm-column>
   <pm-column position='15' dic='-0.7254905914760962' kdic='0.6608037696437961'>
    <a>88.47356031903595</a>
    <c>5.524420979736529</c>
    <g>21.56705986669039</g>
    <t>3.358739708634259</t>
   </pm-column>
   <pm-column position='16' dic='-1.3132010698451908' kdic='0.07309329127469981'>
    <a>25.854109773424415</a>
    <c>24.13042728363671</c>
    <g>33.897585534636576</g>
    <t>35.04165828239931</t>
   </pm-column>
   <pm-column position='17' dic='-0.9637306400207022' kdic='0.42256372109918977'>
    <a>78.22009065125079</a>
    <c>14.451894303577904</c>
    <g>13.125897959634216</g>
    <t>13.125897959634216</t>
   </pm-column>
   <pm-column position='18' dic='-1.2423717051396468' kdic='0.14392265598024429'>
    <a>19.048005085214655</a>
    <c>16.833338124343154</c>
    <g>37.21201260780034</g>
    <t>45.83042505673886</t>
   </pm-column>
   <pm-column position='19' dic='-1.2341923025544583' kdic='0.15210205856543257'>
    <a>52.70243491145875</a>
    <c>19.291160793607247</c>
    <g>20.484219231139296</g>
    <t>26.44596593789171</t>
   </pm-column>
  </WPCM>
  <PPM words-count='118.923780874097' length='19' kdic='12.998239784183168' dic='-13.341353077094775'>
   <pm-column position='1' dic='-1.2624903080943155' kdic='0.1238040530255748'>
    <a>0.25600890988317</a>
    <c>0.152363932208799</c>
    <g>0.395781195180562</g>
    <t>0.195845962727469</t>
   </pm-column>
   <pm-column position='2' dic='-1.0729921409937586' kdic='0.31330222012613185'>
    <a>0.580810509182965</a>
    <c>0.184695994788361</c>
    <g>0.128210409080485</g>
    <t>0.106283086948189</t>
   </pm-column>
   <pm-column position='3' dic='-1.2179349576415375' kdic='0.1683594034783531'>
    <a>0.373441964770467</a>
    <c>0.260137474140672</c>
    <g>0.0780402940942509</g>
    <t>0.28838026699461</t>
   </pm-column>
   <pm-column position='4' dic='-1.1530617573373023' kdic='0.2332326037825874'>
    <a>0.487530977423982</a>
    <c>0.0858462197995774</c>
    <g>0.16723055612761</g>
    <t>0.25939224664883</t>
   </pm-column>
   <pm-column position='5' dic='-0.643981408425648' kdic='0.7423129526942439'>
    <a>0.787473120635501</a>
    <c>0.00706069821348454</c>
    <g>0.0854736060536564</g>
    <t>0.119992575097359</t>
   </pm-column>
   <pm-column position='6' dic='-0.25170837676398783' kdic='1.1345859843559045'>
    <a>0.0141213964269691</a>
    <c>0.0319594488336409</c>
    <g>0.940582280336143</g>
    <t>0.0133368744032486</t>
   </pm-column>
   <pm-column position='7' dic='-0.03374418851274059' kdic='1.3525501726071538'>
    <a>0.992939301786518</a>
    <c>0.0</c>
    <g>0.0</g>
    <t>0.00706069821348454</t>
   </pm-column>
   <pm-column position='8' dic='-0.7806503526954008' kdic='0.6056440084244911'>
    <a>0.0390201470471255</a>
    <c>0.334421817723342</c>
    <g>0.00706069821348454</g>
    <t>0.619497337016049</t>
   </pm-column>
   <pm-column position='9' dic='-0.23692336041937645' kdic='1.1493710007005173'>
    <a>0.943141800546205</a>
    <c>0.0356761048133437</c>
    <g>0.0141213964269691</g>
    <t>0.00706069821348454</t>
   </pm-column>
   <pm-column position='10' dic='-0.23848741451342356' kdic='1.1478069466064698'>
    <a>0.939797758312423</a>
    <c>0.0</c>
    <g>0.0178380524066718</g>
    <t>0.0423641892809072</t>
   </pm-column>
   <pm-column position='11' dic='-0.16690464072168137' kdic='1.2193897203982127'>
    <a>0.0</a>
    <c>0.0286154065998591</c>
    <g>0.960607239206956</g>
    <t>0.0107773541931873</t>
   </pm-column>
   <pm-column position='12' dic='-0.15180888596986264' kdic='1.2344854751500314'>
    <a>0.960607239206956</a>
    <c>0.0</c>
    <g>0.0</g>
    <t>0.0393927607930464</t>
   </pm-column>
   <pm-column position='13' dic='-0.26170503542809265' kdic='1.1245893256918'>
    <a>0.0</a>
    <c>0.0680081673929055</c>
    <g>0.00627617618976404</g>
    <t>0.925715656417332</t>
   </pm-column>
   <pm-column position='14' dic='-0.38997394054155615' kdic='0.9963204205783363'>
    <a>0.885538373600565</a>
    <c>0.0</c>
    <g>0.0286154065998591</g>
    <t>0.0858462197995774</t>
   </pm-column>
   <pm-column position='15' dic='-0.7254905914760962' kdic='0.6608037696437961'>
    <a>0.743951795584953</a>
    <c>0.0464534590065309</c>
    <g>0.181351952554579</g>
    <t>0.0282427928539382</t>
   </pm-column>
   <pm-column position='16' dic='-1.3132010698451908' kdic='0.07309329127469981'>
    <a>0.217400671113844</a>
    <c>0.202906660940954</c>
    <g>0.285036224760828</g>
    <t>0.294656443184374</t>
   </pm-column>
   <pm-column position='17' dic='-0.9637306400207022' kdic='0.42256372109918977'>
    <a>0.657732962039454</a>
    <c>0.121522324612921</c>
    <g>0.110372356673813</g>
    <t>0.110372356673813</t>
   </pm-column>
   <pm-column position='18' dic='-1.2423717051396468' kdic='0.14392265598024429'>
    <a>0.160169857914125</a>
    <c>0.141547283483733</c>
    <g>0.312906403868846</g>
    <t>0.385376454733296</t>
   </pm-column>
   <pm-column position='19' dic='-1.2341923025544583' kdic='0.15210205856543257'>
    <a>0.443161447812142</a>
    <c>0.162214492776937</c>
    <g>0.172246619478283</g>
    <t>0.222377439932638</t>
   </pm-column>
  </PPM>
  <PWM length='19' words-count='118.923780874097'>
   <pm-column position='1'>
    <a>0.02284424114581235</a>
    <c>-0.47073665664186076</c>
    <g>0.4450699205045081</g>
    <t>-0.23350770508560253</t>
   </pm-column>
   <pm-column position='2'>
    <a>0.8207162422393699</a>
    <c>-0.28918390953257117</c>
    <g>-0.6317510358633617</g>
    <t>-0.8044389071552667</t>
   </pm-column>
   <pm-column position='3'>
    <a>0.38845061111138246</a>
    <c>0.03824282991809627</c>
    <g>-1.082547119812033</g>
    <t>0.13766471645228914</t>
   </pm-column>
   <pm-column position='4'>
    <a>0.6488930869682571</a>
    <c>-0.9976385374109306</c>
    <g>-0.38314888385243107</g>
    <t>0.03548078394567786</t>
   </pm-column>
   <pm-column position='5'>
    <a>1.120649180734762</a>
    <c>-2.7214286733365416</c>
    <g>-1.0015318923065302</g>
    <t>-0.6930302325774347</t>
   </pm-column>
   <pm-column position='6'>
    <a>-2.3758817174737406</a>
    <c>-1.8230738987816697</c>
    <g>1.2962666331354433</g>
    <t>-2.40888331858163</t>
   </pm-column>
   <pm-column position='7'>
    <a>1.3498796934675004</a>
    <c>-3.2537544904797753</c>
    <g>-3.2537544904797753</g>
    <t>-2.7214286733365416</t>
   </pm-column>
   <pm-column position='8'>
    <a>-1.6677013916495853</a>
    <c>0.2811428245490298</c>
    <g>-2.7214286733365416</g>
    <t>0.8841378188551877</t>
   </pm-column>
   <pm-column position='9'>
    <a>1.2989554682162718</a>
    <c>-1.738289942313802</c>
    <g>-2.3758817174737406</g>
    <t>-2.7214286733365416</t>
   </pm-column>
   <pm-column position='10'>
    <a>1.2954410249070551</a>
    <c>-3.2537544904797753</c>
    <g>-2.2328271971893074</g>
    <t>-1.601768736854747</t>
   </pm-column>
   <pm-column position='11'>
    <a>-3.2537544904797753</a>
    <c>-1.906032902707689</c>
    <g>1.3171128227174542</g>
    <t>-2.5248159277384574</t>
   </pm-column>
   <pm-column position='12'>
    <a>1.3171128227174542</a>
    <c>-3.2537544904797753</c>
    <g>-3.2537544904797753</g>
    <t>-1.6601358580228045</t>
   </pm-column>
   <pm-column position='13'>
    <a>-3.2537544904797753</a>
    <c>-1.2034621039463143</c>
    <g>-2.7683761527850517</g>
    <t>1.2805043105729477</t>
   </pm-column>
   <pm-column position='14'>
    <a>1.2366199083909333</a>
    <c>-3.2537544904797753</c>
    <g>-1.906032902707689</g>
    <t>-0.9976385374109306</t>
   </pm-column>
   <pm-column position='15'>
    <a>1.0645327617057798</a>
    <c>-1.5266376808979216</c>
    <g>-0.3065047727078454</g>
    <t>-1.9157177065237314</t>
   </pm-column>
   <pm-column position='16'>
    <a>-0.13394314623071465</a>
    <c>-0.19978927298973645</c>
    <g>0.1263958434067398</g>
    <t>0.15847758100674686</t>
   </pm-column>
   <pm-column position='17'>
    <a>0.943100414815799</a>
    <c>-0.6813350091804627</c>
    <g>-0.7698898377799718</g>
    <t>-0.7698898377799718</t>
   </pm-column>
   <pm-column position='18'>
    <a>-0.4237926493832413</a>
    <c>-0.5396593970304707</c>
    <g>0.21664696925928872</g>
    <t>0.41909713042058705</t>
   </pm-column>
   <pm-column position='19'>
    <a>0.555492631758211</a>
    <c>-0.41185215803290026</c>
    <g>-0.35524655142321726</g>
    <t>-0.11229799491891874</t>
   </pm-column>
  </PWM>
 </motif>
</smallbismark>